// 
// Decompiled by Procyon v0.5.34
// 

package android.support.v4.view;

import android.os.Build$VERSION;
import android.view.Window$Callback;
import android.content.DialogInterface$OnKeyListener;
import android.content.DialogInterface;
import android.app.Dialog;
import android.view.KeyEvent$DispatcherState;
import android.view.View;
import android.view.Window;
import android.view.KeyEvent$Callback;
import android.app.Activity;
import android.view.KeyEvent;
import android.app.ActionBar;
import java.lang.reflect.Field;
import java.lang.reflect.Method;

public class KeyEventDispatcher
{
    private static boolean sActionBarFieldsFetched = false;
    private static Method sActionBarOnMenuKeyMethod;
    private static boolean sDialogFieldsFetched = false;
    private static Field sDialogKeyListenerField;
    
    private static boolean actionBarOnMenuKeyEventPre28(final ActionBar p0, final KeyEvent p1) {
        // 
        // This method could not be decompiled.
        // 
        // Original Bytecode:
        // 
        //     3: ifne            31
        //     6: aload_0        
        //     7: invokevirtual   java/lang/Object.getClass:()Ljava/lang/Class;
        //    10: ldc             "onMenuKeyEvent"
        //    12: iconst_1       
        //    13: anewarray       Ljava/lang/Class;
        //    16: dup            
        //    17: iconst_0       
        //    18: ldc             Landroid/view/KeyEvent;.class
        //    20: aastore        
        //    21: invokevirtual   java/lang/Class.getMethod:(Ljava/lang/String;[Ljava/lang/Class;)Ljava/lang/reflect/Method;
        //    24: putstatic       android/support/v4/view/KeyEventDispatcher.sActionBarOnMenuKeyMethod:Ljava/lang/reflect/Method;
        //    27: iconst_1       
        //    28: putstatic       android/support/v4/view/KeyEventDispatcher.sActionBarFieldsFetched:Z
        //    31: getstatic       android/support/v4/view/KeyEventDispatcher.sActionBarOnMenuKeyMethod:Ljava/lang/reflect/Method;
        //    34: ifnull          61
        //    37: getstatic       android/support/v4/view/KeyEventDispatcher.sActionBarOnMenuKeyMethod:Ljava/lang/reflect/Method;
        //    40: aload_0        
        //    41: iconst_1       
        //    42: anewarray       Ljava/lang/Object;
        //    45: dup            
        //    46: iconst_0       
        //    47: aload_1        
        //    48: aastore        
        //    49: invokevirtual   java/lang/reflect/Method.invoke:(Ljava/lang/Object;[Ljava/lang/Object;)Ljava/lang/Object;
        //    52: checkcast       Ljava/lang/Boolean;
        //    55: invokevirtual   java/lang/Boolean.booleanValue:()Z
        //    58: istore_2       
        //    59: iload_2        
        //    60: ireturn        
        //    61: iconst_0       
        //    62: ireturn        
        //    63: astore_3       
        //    64: goto            27
        //    67: astore_0       
        //    68: goto            61
        //    Exceptions:
        //  Try           Handler
        //  Start  End    Start  End    Type                                         
        //  -----  -----  -----  -----  ---------------------------------------------
        //  6      27     63     67     Ljava/lang/NoSuchMethodException;
        //  37     59     67     71     Ljava/lang/IllegalAccessException;
        //  37     59     67     71     Ljava/lang/reflect/InvocationTargetException;
        // 
        // The error that occurred was:
        // 
        // java.lang.IllegalStateException: Expression is linked from several locations: Label_0061:
        //     at com.strobel.decompiler.ast.Error.expressionLinkedFromMultipleLocations(Error.java:27)
        //     at com.strobel.decompiler.ast.AstOptimizer.mergeDisparateObjectInitializations(AstOptimizer.java:2596)
        //     at com.strobel.decompiler.ast.AstOptimizer.optimize(AstOptimizer.java:235)
        //     at com.strobel.decompiler.ast.AstOptimizer.optimize(AstOptimizer.java:42)
        //     at com.strobel.decompiler.languages.java.ast.AstMethodBodyBuilder.createMethodBody(AstMethodBodyBuilder.java:214)
        //     at com.strobel.decompiler.languages.java.ast.AstMethodBodyBuilder.createMethodBody(AstMethodBodyBuilder.java:99)
        //     at com.strobel.decompiler.languages.java.ast.AstBuilder.createMethodBody(AstBuilder.java:782)
        //     at com.strobel.decompiler.languages.java.ast.AstBuilder.createMethod(AstBuilder.java:675)
        //     at com.strobel.decompiler.languages.java.ast.AstBuilder.addTypeMembers(AstBuilder.java:552)
        //     at com.strobel.decompiler.languages.java.ast.AstBuilder.createTypeCore(AstBuilder.java:519)
        //     at com.strobel.decompiler.languages.java.ast.AstBuilder.createTypeNoCache(AstBuilder.java:161)
        //     at com.strobel.decompiler.languages.java.ast.AstBuilder.createType(AstBuilder.java:150)
        //     at com.strobel.decompiler.languages.java.ast.AstBuilder.addType(AstBuilder.java:125)
        //     at com.strobel.decompiler.languages.java.JavaLanguage.buildAst(JavaLanguage.java:71)
        //     at com.strobel.decompiler.languages.java.JavaLanguage.decompileType(JavaLanguage.java:59)
        //     at com.strobel.decompiler.DecompilerDriver.decompileType(DecompilerDriver.java:330)
        //     at com.strobel.decompiler.DecompilerDriver.decompileJar(DecompilerDriver.java:251)
        //     at com.strobel.decompiler.DecompilerDriver.main(DecompilerDriver.java:126)
        // 
        throw new IllegalStateException("An error occurred while decompiling this method.");
    }
    
    private static boolean activitySuperDispatchKeyEventPre28(final Activity activity, final KeyEvent keyEvent) {
        activity.onUserInteraction();
        final Window window = activity.getWindow();
        if (window.hasFeature(8)) {
            final ActionBar actionBar = activity.getActionBar();
            if (keyEvent.getKeyCode() == 82 && actionBar != null && actionBarOnMenuKeyEventPre28(actionBar, keyEvent)) {
                return true;
            }
        }
        if (window.superDispatchKeyEvent(keyEvent)) {
            return true;
        }
        final View decorView = window.getDecorView();
        if (ViewCompat.dispatchUnhandledKeyEventBeforeCallback(decorView, keyEvent)) {
            return true;
        }
        KeyEvent$DispatcherState keyDispatcherState;
        if (decorView != null) {
            keyDispatcherState = decorView.getKeyDispatcherState();
        }
        else {
            keyDispatcherState = null;
        }
        return keyEvent.dispatch((KeyEvent$Callback)activity, keyDispatcherState, (Object)activity);
    }
    
    private static boolean dialogSuperDispatchKeyEventPre28(final Dialog dialog, final KeyEvent keyEvent) {
        final DialogInterface$OnKeyListener dialogKeyListenerPre28 = getDialogKeyListenerPre28(dialog);
        if (dialogKeyListenerPre28 != null && dialogKeyListenerPre28.onKey((DialogInterface)dialog, keyEvent.getKeyCode(), keyEvent)) {
            return true;
        }
        final Window window = dialog.getWindow();
        if (window.superDispatchKeyEvent(keyEvent)) {
            return true;
        }
        final View decorView = window.getDecorView();
        if (ViewCompat.dispatchUnhandledKeyEventBeforeCallback(decorView, keyEvent)) {
            return true;
        }
        KeyEvent$DispatcherState keyDispatcherState;
        if (decorView != null) {
            keyDispatcherState = decorView.getKeyDispatcherState();
        }
        else {
            keyDispatcherState = null;
        }
        return keyEvent.dispatch((KeyEvent$Callback)dialog, keyDispatcherState, (Object)dialog);
    }
    
    public static boolean dispatchBeforeHierarchy(final View view, final KeyEvent keyEvent) {
        return ViewCompat.dispatchUnhandledKeyEventBeforeHierarchy(view, keyEvent);
    }
    
    public static boolean dispatchKeyEvent(final Component component, final View view, final Window$Callback window$Callback, final KeyEvent keyEvent) {
        boolean b = false;
        if (component == null) {
            return false;
        }
        if (Build$VERSION.SDK_INT >= 28) {
            return component.superDispatchKeyEvent(keyEvent);
        }
        if (window$Callback instanceof Activity) {
            return activitySuperDispatchKeyEventPre28((Activity)window$Callback, keyEvent);
        }
        if (window$Callback instanceof Dialog) {
            return dialogSuperDispatchKeyEventPre28((Dialog)window$Callback, keyEvent);
        }
        if ((view != null && ViewCompat.dispatchUnhandledKeyEventBeforeCallback(view, keyEvent)) || component.superDispatchKeyEvent(keyEvent)) {
            b = true;
        }
        return b;
    }
    
    private static DialogInterface$OnKeyListener getDialogKeyListenerPre28(final Dialog p0) {
        // 
        // This method could not be decompiled.
        // 
        // Original Bytecode:
        // 
        //     3: ifne            27
        //     6: ldc             Landroid/app/Dialog;.class
        //     8: ldc             "mOnKeyListener"
        //    10: invokevirtual   java/lang/Class.getDeclaredField:(Ljava/lang/String;)Ljava/lang/reflect/Field;
        //    13: putstatic       android/support/v4/view/KeyEventDispatcher.sDialogKeyListenerField:Ljava/lang/reflect/Field;
        //    16: getstatic       android/support/v4/view/KeyEventDispatcher.sDialogKeyListenerField:Ljava/lang/reflect/Field;
        //    19: iconst_1       
        //    20: invokevirtual   java/lang/reflect/Field.setAccessible:(Z)V
        //    23: iconst_1       
        //    24: putstatic       android/support/v4/view/KeyEventDispatcher.sDialogFieldsFetched:Z
        //    27: getstatic       android/support/v4/view/KeyEventDispatcher.sDialogKeyListenerField:Ljava/lang/reflect/Field;
        //    30: ifnull          46
        //    33: getstatic       android/support/v4/view/KeyEventDispatcher.sDialogKeyListenerField:Ljava/lang/reflect/Field;
        //    36: aload_0        
        //    37: invokevirtual   java/lang/reflect/Field.get:(Ljava/lang/Object;)Ljava/lang/Object;
        //    40: checkcast       Landroid/content/DialogInterface$OnKeyListener;
        //    43: astore_0       
        //    44: aload_0        
        //    45: areturn        
        //    46: aconst_null    
        //    47: areturn        
        //    48: astore_1       
        //    49: goto            23
        //    52: astore_0       
        //    53: goto            46
        //    Exceptions:
        //  Try           Handler
        //  Start  End    Start  End    Type                              
        //  -----  -----  -----  -----  ----------------------------------
        //  6      23     48     52     Ljava/lang/NoSuchFieldException;
        //  33     44     52     56     Ljava/lang/IllegalAccessException;
        // 
        // The error that occurred was:
        // 
        // java.lang.IllegalStateException: Expression is linked from several locations: Label_0046:
        //     at com.strobel.decompiler.ast.Error.expressionLinkedFromMultipleLocations(Error.java:27)
        //     at com.strobel.decompiler.ast.AstOptimizer.mergeDisparateObjectInitializations(AstOptimizer.java:2596)
        //     at com.strobel.decompiler.ast.AstOptimizer.optimize(AstOptimizer.java:235)
        //     at com.strobel.decompiler.ast.AstOptimizer.optimize(AstOptimizer.java:42)
        //     at com.strobel.decompiler.languages.java.ast.AstMethodBodyBuilder.createMethodBody(AstMethodBodyBuilder.java:214)
        //     at com.strobel.decompiler.languages.java.ast.AstMethodBodyBuilder.createMethodBody(AstMethodBodyBuilder.java:99)
        //     at com.strobel.decompiler.languages.java.ast.AstBuilder.createMethodBody(AstBuilder.java:782)
        //     at com.strobel.decompiler.languages.java.ast.AstBuilder.createMethod(AstBuilder.java:675)
        //     at com.strobel.decompiler.languages.java.ast.AstBuilder.addTypeMembers(AstBuilder.java:552)
        //     at com.strobel.decompiler.languages.java.ast.AstBuilder.createTypeCore(AstBuilder.java:519)
        //     at com.strobel.decompiler.languages.java.ast.AstBuilder.createTypeNoCache(AstBuilder.java:161)
        //     at com.strobel.decompiler.languages.java.ast.AstBuilder.createType(AstBuilder.java:150)
        //     at com.strobel.decompiler.languages.java.ast.AstBuilder.addType(AstBuilder.java:125)
        //     at com.strobel.decompiler.languages.java.JavaLanguage.buildAst(JavaLanguage.java:71)
        //     at com.strobel.decompiler.languages.java.JavaLanguage.decompileType(JavaLanguage.java:59)
        //     at com.strobel.decompiler.DecompilerDriver.decompileType(DecompilerDriver.java:330)
        //     at com.strobel.decompiler.DecompilerDriver.decompileJar(DecompilerDriver.java:251)
        //     at com.strobel.decompiler.DecompilerDriver.main(DecompilerDriver.java:126)
        // 
        throw new IllegalStateException("An error occurred while decompiling this method.");
    }
    
    public interface Component
    {
        boolean superDispatchKeyEvent(final KeyEvent p0);
    }
}
